README.rst
setup.py
escposprinter/__init__.py
escposprinter/constants.py
escposprinter/escpos.py
escposprinter/exceptions.py
escposprinter/nc.exe
escposprinter/printer.py
escposprinter.egg-info/PKG-INFO
escposprinter.egg-info/SOURCES.txt
escposprinter.egg-info/dependency_links.txt
escposprinter.egg-info/requires.txt
escposprinter.egg-info/top_level.txt